billjobs/__init__.py
billjobs/admin.py
billjobs/models.py
billjobs/settings.py
billjobs/urls.py
billjobs/views.py
billjobs/locale/fr/LC_MESSAGES/django.mo
billjobs/locale/fr/LC_MESSAGES/django.po
billjobs/migrations/0001_initial.py
billjobs/migrations/0002_service_is_available.py
billjobs/migrations/0002_service_is_available_squashed_0005_bill_issuer_address_default.py
billjobs/migrations/0003_billline_note.py
billjobs/migrations/0004_auto_20160321_1256.py
billjobs/migrations/0005_bill_issuer_address_default.py
billjobs/migrations/0006_add_billin_address_and_migrate_data.py
billjobs/migrations/0007_change_service_description_field_max_len.py
billjobs/migrations/0008_auto_20180308_1312.py
billjobs/migrations/0009_auto_20190114_2126.py
billjobs/migrations/0010_quote_quoteline.py
billjobs/migrations/__init__.py
billjobs/static/css/bulma.css
billjobs/static/css/font-awesome.min.css
billjobs/static/fonts/fontawesome-webfont.ttf
billjobs/static/fonts/fontawesome-webfont.woff
billjobs/static/fonts/fontawesome-webfont.woff2
billjobs/static/images/logo-default.png
billjobs/templates/billjobs/admin_index.html
billjobs/templates/billjobs/base.html
billjobs/templates/billjobs/signup.html
billjobs/templates/billjobs/signup_success.html
billjobs/templates/billjobs/statistics.html
billjobs/tests/__init__.py
billjobs/tests/factories.py
billjobs/tests/tests_export_account_email.py
billjobs/tests/tests_fn_billing.py
billjobs/tests/tests_model.py
billjobs/tests/tests_signup.py
billjobs/tests/tests_statistics.py
django_billjobs-0.13.2.dist-info/LICENSE
django_billjobs-0.13.2.dist-info/METADATA
django_billjobs-0.13.2.dist-info/WHEEL
django_billjobs-0.13.2.dist-info/top_level.txt
django_billjobs-0.13.2.dist-info/RECORD
