Metadata-Version: 2.1
Name: django-billjobs
Version: 0.13.2
Summary: A django billing app for coworking space.
Home-page: https://github.com/ioO/django-billjobs
Author: Lionel Chanson
Author-email: github@lionelchanson.fr
License: X11 License
Classifier: Development Status :: 5 - Production/Stable
Classifier: Environment :: Web Environment
Classifier: Framework :: Django
Classifier: Framework :: Django :: 4.2
Classifier: Intended Audience :: Other Audience
Classifier: License :: OSI Approved :: MIT License
Classifier: Natural Language :: English
Classifier: Operating System :: OS Independent
Classifier: Programming Language :: Python
Classifier: Programming Language :: Python :: 3.10
Classifier: Programming Language :: Python :: 3.11
Classifier: Programming Language :: Python :: 3.12
Classifier: Topic :: Internet :: WWW/HTTP
Requires-Python: >=3.10
License-File: LICENSE
Requires-Dist: django <5
Requires-Dist: reportlab <3.7
Requires-Dist: requests <3
Requires-Dist: python-dateutil
